{
  "items": [
    {
      "title": "Selenskyj im ARD-Gespräch: \"Bin bereit zu einem Treffen mit Putin\"",
      "link": "https://www.tagesschau.de/ausland/europa/ukraine-interview-selenskyj-102.html"
    },
    {
      "title": "Proteste in Iran: \"Wir werden keinen mörderischen Führer loben\"",
      "link": "https://www.tagesschau.de/ausland/asien/iran-proteste-304.html"
    },
    {
      "title": "Marktbericht: Die Zollunsicherheit ist zurück",
      "link": "https://www.tagesschau.de/wirtschaft/finanzen/marktberichte/marktbericht-dax-dow-zollstreit-geldanlage-100.html"
    },
    {
      "title": "Ungarn blockiert neue EU-Sanktionen gegen Russland",
      "link": "https://www.tagesschau.de/ausland/europa/eu-sanktionen-ungarn-100.html"
    },
    {
      "title": "Chaos und Gewalt in Mexiko nach Tod von Drogenboss \"El Mencho\"",
      "link": "https://www.tagesschau.de/ausland/amerika/mexiko-tod-drogenboss-chaos-gewalt-100.html"
    },
    {
      "title": "Tödliche Messerangriff auf Frau im nordrhein-westfälischen Hagen",
      "link": "https://www.tagesschau.de/inland/regional/nordrheinwestfalen/messerangriff-hagen-100.html"
    },
    {
      "title": "Wintersturm trifft Nordosten der USA schwer",
      "link": "https://www.tagesschau.de/ausland/usa-wintersturm-138.html"
    },
    {
      "title": "EU-Parlament stoppt Umsetzung von Zolldeal mit den USA vorerst",
      "link": "https://www.tagesschau.de/wirtschaft/eu-parlament-zolldeal-usa-100.html"
    },
    {
      "title": "Wieso das Lehramtsstudium reformiert werden sollte",
      "link": "https://www.tagesschau.de/wissen/forschung/schule-lehrkraefte-studium-100.html"
    },
    {
      "title": "Iran, ein Land im Wartezustand: Eine Reportage aus Teheran",
      "link": "https://www.tagesschau.de/ausland/asien/iran-stimmung-bevoelkerung-100.html"
    },
    {
      "title": "Schulen in Solingen: Was bringt ein Social-Media-Verbot?",
      "link": "https://www.tagesschau.de/inland/gesellschaft/social-media-verbot-schule-100.html"
    },
    {
      "title": "DAX unter Druck: Neue Zollsorgen belasten Börsen",
      "link": "https://www.tagesschau.de/wirtschaft/finanzen/marktbericht-zollunsicherheit-100.html"
    },
    {
      "title": "Polen nimmt mutmaßlichen belarusischen Spion fest",
      "link": "https://www.tagesschau.de/ausland/europa/polen-warschau-festnahme-spion-belarus-100.html"
    },
    {
      "title": "Ministerpräsident Günther will Zuckersteuer über Bundesrat durchsetzen",
      "link": "https://www.tagesschau.de/inland/daniel-guenther-zuckersteuer-100.html"
    },
    {
      "title": "Die EU-Außenminister beraten erneut über den Ukraine-Krieg",
      "link": "https://www.tagesschau.de/ausland/europa/ukraine-krieg-treffen-aussenminister-100.html"
    },
    {
      "title": "Bus prallt gegen Baum - zwölf Menschen verletzt",
      "link": "https://www.tagesschau.de/inland/regional/berlin/busunfall-berlin-100.html"
    },
    {
      "title": "ifo-Geschäftsklima-Index steigt: \"Erste Signale einer Belebung\"",
      "link": "https://www.tagesschau.de/wirtschaft/konjunktur/ifo-stimmung-unternehmen-102.html"
    },
    {
      "title": "US-Zölle: Maschinenbau-Exporte 2025 gesunken - Branchenverband warnt",
      "link": "https://www.tagesschau.de/wirtschaft/konjunktur/us-zoelle-maschinenbau-exporte-vdma-100.html"
    },
    {
      "title": "Wie Deutschland bei wichtigen Rohstoffen unabhängiger werden kann",
      "link": "https://www.tagesschau.de/wirtschaft/unternehmen/rohstoffe-mangel-problem-unternehmen-100.html"
    },
    {
      "title": "Vereidigung von Rob Jetten: Neue Töne aus den Niederlanden",
      "link": "https://www.tagesschau.de/ausland/europa/niederlande-minderheitsregierung-vereidigung-100.html"
    }
  ]
}